git2md.py
converters/__init__.py
converters/base.py
converters/default.py
exporters/__init__.py
exporters/base.py
exporters/markdown.py
utils/__init__.py
utils/clipboard.py
utils/ignore.py
utils/tree.py
utils/loggers/__init__.py
utils/loggers/multiline.py
git2md-1.1.6.dist-info/LICENSE
git2md-1.1.6.dist-info/METADATA
git2md-1.1.6.dist-info/WHEEL
git2md-1.1.6.dist-info/entry_points.txt
git2md-1.1.6.dist-info/top_level.txt
git2md-1.1.6.dist-info/RECORD
